power_sysGraph/__init__.py
power_sysGraph/p_system.py
power_sysGraph-0.0.13.dist-info/LICENSE
power_sysGraph-0.0.13.dist-info/METADATA
power_sysGraph-0.0.13.dist-info/WHEEL
power_sysGraph-0.0.13.dist-info/top_level.txt
power_sysGraph-0.0.13.dist-info/RECORD
